dompa/__init__.py
dompa/dompa.py
dompa/dompa_test.py
dompa/serializer.py
dompa/utils.py
dompa/nodes/__init__.py
dompa/nodes/fragment_node.py
dompa/nodes/ir_node.py
dompa/nodes/node.py
dompa/nodes/node_test.py
dompa/nodes/serializer.py
dompa/nodes/text_node.py
dompa/nodes/void_node.py
dompa/nodes/serializers/__init__.py
dompa/nodes/serializers/to_html.py
dompa/serializers/__init__.py
dompa/serializers/to_html.py
dompa-0.9.0.dist-info/LICENSE.txt
dompa-0.9.0.dist-info/METADATA
dompa-0.9.0.dist-info/WHEEL
dompa-0.9.0.dist-info/top_level.txt
dompa-0.9.0.dist-info/RECORD
