Metadata-Version: 2.2
Name: dompa
Version: 0.9.0
Summary: A zero-dependency, extendable HTML5 parser.
Author-email: Asko Nõmm <asko@nmm.ee>
Classifier: Programming Language :: Python :: 3
Classifier: License :: OSI Approved :: MIT License
Classifier: Operating System :: OS Independent
Classifier: Development Status :: 4 - Beta
Requires-Python: >=3.10
License-File: LICENSE.txt
